google/cloud/bigtable/__init__.py
google/cloud/bigtable/app_profile.py
google/cloud/bigtable/backup.py
google/cloud/bigtable/batcher.py
google/cloud/bigtable/client.py
google/cloud/bigtable/cluster.py
google/cloud/bigtable/column_family.py
google/cloud/bigtable/encryption_info.py
google/cloud/bigtable/enums.py
google/cloud/bigtable/error.py
google/cloud/bigtable/gapic_version.py
google/cloud/bigtable/helpers.py
google/cloud/bigtable/instance.py
google/cloud/bigtable/policy.py
google/cloud/bigtable/py.typed
google/cloud/bigtable/row.py
google/cloud/bigtable/row_data.py
google/cloud/bigtable/row_filters.py
google/cloud/bigtable/row_merger.py
google/cloud/bigtable/row_set.py
google/cloud/bigtable/table.py
google/cloud/bigtable/data/__init__.py
google/cloud/bigtable/data/_helpers.py
google/cloud/bigtable/data/exceptions.py
google/cloud/bigtable/data/mutations.py
google/cloud/bigtable/data/read_modify_write_rules.py
google/cloud/bigtable/data/read_rows_query.py
google/cloud/bigtable/data/row.py
google/cloud/bigtable/data/row_filters.py
google/cloud/bigtable/data/_async/__init__.py
google/cloud/bigtable/data/_async/_mutate_rows.py
google/cloud/bigtable/data/_async/_read_rows.py
google/cloud/bigtable/data/_async/client.py
google/cloud/bigtable/data/_async/mutations_batcher.py
google/cloud/bigtable/data/_cross_sync/__init__.py
google/cloud/bigtable/data/_cross_sync/_decorators.py
google/cloud/bigtable/data/_cross_sync/_mapping_meta.py
google/cloud/bigtable/data/_cross_sync/cross_sync.py
google/cloud/bigtable/data/_sync_autogen/_mutate_rows.py
google/cloud/bigtable/data/_sync_autogen/_read_rows.py
google/cloud/bigtable/data/_sync_autogen/client.py
google/cloud/bigtable/data/_sync_autogen/mutations_batcher.py
google/cloud/bigtable/data/execute_query/__init__.py
google/cloud/bigtable/data/execute_query/_byte_cursor.py
google/cloud/bigtable/data/execute_query/_checksum.py
google/cloud/bigtable/data/execute_query/_parameters_formatting.py
google_cloud_bigtable-2.31.0.dist-info/LICENSE
google_cloud_bigtable-2.31.0.dist-info/METADATA
google_cloud_bigtable-2.31.0.dist-info/WHEEL
google_cloud_bigtable-2.31.0.dist-info/top_level.txt
google_cloud_bigtable-2.31.0.dist-info/RECORD
