Metadata-Version: 2.1
Name: google-cloud-bigtable
Version: 2.31.0
Summary: Google Cloud Bigtable API client library
Home-page: https://github.com/googleapis/python-bigtable
Author: Google LLC
Author-email: googleapis-packages@google.com
License: Apache 2.0
Platform: Posix; MacOS X; Windows
Classifier: Development Status :: 5 - Production/Stable
Classifier: Intended Audience :: Developers
Classifier: License :: OSI Approved :: Apache Software License
Classifier: Programming Language :: Python
Classifier: Programming Language :: Python :: 3.7
Classifier: Programming Language :: Python :: 3.8
Classifier: Programming Language :: Python :: 3.9
Classifier: Programming Language :: Python :: 3.10
Classifier: Programming Language :: Python :: 3.11
Classifier: Programming Language :: Python :: 3.12
Classifier: Operating System :: OS Independent
Classifier: Topic :: Internet
Requires-Python: >=3.7
License-File: LICENSE
Requires-Dist: google-api-core[grpc]<3.0.0,>=2.16.0
Requires-Dist: google-cloud-core<3.0.0,>=1.4.4
Requires-Dist: google-auth!=2.24.0,!=2.25.0,<3.0.0,>=2.14.1
Requires-Dist: grpc-google-iam-v1<1.0.0,>=0.12.4
Requires-Dist: proto-plus<2.0.0,>=1.22.3
Requires-Dist: proto-plus<2.0.0,>=1.25.0; python_version >= "3.13"
Requires-Dist: protobuf!=4.21.0,!=4.21.1,!=4.21.2,!=4.21.3,!=4.21.4,!=4.21.5,<7.0.0,>=3.20.2
Requires-Dist: google-crc32c<2.0.0dev,>=1.5.0
Provides-Extra: libcst
Requires-Dist: libcst>=0.2.5; extra == "libcst"
